{"list":[{"date":"2018-12","arr":{"year":2018,"month":12,"src":["","","","","",""],"link":["005SXcCcly1fwv5xwj3sqj30u011kthm","005SXcCcly1fwv5xzvg10j30u011cwmh","005SXcCcly1fwv5y2ddncj30u011k49c","005SXcCcly1fwv5y3qux2j30u011igsm","005SXcCcly1fwv5y4vf3ij30u011kk2s","005SXcCcly1fwv5y5tnfwj30u011kqd0"],"text":["唐田英里佳","唐田英里佳","唐田英里佳","唐田英里佳","唐田英里佳","唐田英里佳"],"type":["image","image","image","image","image","image"]}},{"date":"2017-06","arr":{"year":2017,"month":6,"src":["","","","","","",""],"link":["pic1","pic2","pic3","pic4","pic5","pic6","pic7"],"text":["words1\nwords2\nwords3","words1","words1","words1","words1","words1","words1"],"type":["image","image","image","image","image","image","image"]}},{"date":"2017-05","arr":{"year":2017,"month":5,"src":["","","","","","","","","","","","","",""],"link":["pic1","pic2","pic3","pic4","pic5","pic6","pic7"],"text":["words1\nwords2\nwords3","words1","words1","words1","words1","words1","words1"],"type":["image","image","image","image","image","image","image","image","image","image","image","video","image","image"]}},{"date":"2017-04","arr":{"year":2017,"month":4,"src":["","","","","",""],"link":["pic1","pic2","pic3","pic4","pic5","pic6","pic7"],"text":["words1\nwords2\nwords3","words1","words1","words1","words1","words1","words1"],"type":["image","image","image","image","image","image"]}},{"date":"2017-03","arr":{"year":2017,"month":3,"src":["","","","","","","",""],"link":["pic1","pic2","pic3","pic4","pic5","pic6","pic7"],"text":["words1\nwords2\nwords3","words1","words1","words1","words1","words1","words1"],"type":["image","image","image","image","image","image","image","image"]}},{"date":"2017-02","arr":{"year":2017,"month":2,"src":["","","","",""],"link":["pic1","pic2","pic3","pic4","pic5","pic6","pic7"],"text":["words1\nwords2\nwords3","words1","words1","words1","words1","words1","words1"],"type":["image","image","image","image","image"]}},{"date":"2017-01","arr":{"year":2017,"month":1,"src":["","","","",""],"link":["pic1","pic2","pic3","pic4","pic5","pic6","pic7"],"text":["words1\nwords2\nwords3","words1","words1","words1","words1","words1","words1"],"type":["image","image","video","image","image"]}},{"date":"2016-12","arr":{"year":2016,"month":12,"src":["","","","","","","","","","","","","",""],"link":["pic1","pic2","pic3","pic4","pic5","pic6","pic7"],"text":["words1\nwords2\nwords3","words1","words1","words1","words1","words1","words1"],"type":["image","image","image","image","image","image","image","image","image","image","image","image","image","image"]}},{"date":"2016-11","arr":{"year":2016,"month":11,"src":["","","","","","","","","","","","",""],"link":["pic1","pic2","pic3","pic4","pic5","pic6","pic7"],"text":["words1\nwords2\nwords3","words1","words1","words1","words1","words1","words1"],"type":["image","video","image","image","image","image","image","image","image","image","image","image","image"]}},{"date":"2016-10","arr":{"year":2016,"month":10,"src":["","","","","","","","","","","","",""],"link":["pic1","pic2","pic3","pic4","pic5","pic6","pic7"],"text":["words1\nwords2\nwords3","words1","words1","words1","words1","words1","words1"],"type":["video","image","image","image","image","image","image","image","image","image","image","image","image"]}},{"date":"2016-09","arr":{"year":2016,"month":9,"src":["","","","","","","","","",""],"link":["pic1","pic2","pic3","pic4","pic5","pic6","pic7"],"text":["words1\nwords2\nwords3","words1","words1","words1","words1","words1","words1"],"type":["image","image","image","image","image","image","image","image","image","image"]}},{"date":"2015-12","arr":{"year":2015,"month":12,"src":["url"],"link":["pic1"],"text":["words1"],"type":["video"]}},{"date":"2015-11","arr":{"year":2015,"month":11,"src":["url1","url2","url3","url4"],"link":["pic1","pic2","pic3","pic4"],"text":["words1\nwords2\nwords3","words1","words1","words1","words1","words1","words1"],"type":["image","image","image","video"]}}]}